{
  "annotations": {
    "list": [
      {
        "builtIn": 1,
        "datasource": {
          "type": "grafana",
          "uid": "-- Grafana --"
        },
        "enable": true,
        "hide": true,
        "iconColor": "rgba(0, 211, 255, 1)",
        "name": "Annotations & Alerts",
        "type": "dashboard"
      }
    ]
  },
  "editable": true,
  "fiscalYearStartMonth": 0,
  "graphTooltip": 0,
  "id": null,
  "links": [],
  "liveNow": false,
  "panels": [
    {
      "gridPos": { "h": 1, "w": 24, "x": 0, "y": 0 },
      "id": 100,
      "title": "Adaptive Scaling Overview",
      "type": "row"
    },
    {
      "datasource": { "type": "prometheus", "uid": "prometheus" },
      "fieldConfig": {
        "defaults": {
          "color": { "mode": "thresholds" },
          "mappings": [],
          "thresholds": {
            "mode": "absolute",
            "steps": [
              { "color": "green", "value": null },
              { "color": "yellow", "value": 3000 },
              { "color": "red", "value": 6000 }
            ]
          },
          "unit": "decmbytes"
        },
        "overrides": []
      },
      "gridPos": { "h": 4, "w": 4, "x": 0, "y": 1 },
      "id": 1,
      "options": {
        "colorMode": "value",
        "graphMode": "none",
        "justifyMode": "auto",
        "orientation": "auto",
        "reduceOptions": { "calcs": ["lastNotNull"], "fields": "", "values": false },
        "textMode": "auto"
      },
      "pluginVersion": "10.2.0",
      "targets": [
        {
          "expr": "tavana_adaptive_threshold_mb",
          "legendFormat": "Threshold",
          "refId": "A"
        }
      ],
      "title": "Current Threshold",
      "type": "stat"
    },
    {
      "datasource": { "type": "prometheus", "uid": "prometheus" },
      "fieldConfig": {
        "defaults": {
          "color": { "mode": "thresholds" },
          "mappings": [],
          "thresholds": {
            "mode": "absolute",
            "steps": [
              { "color": "blue", "value": null }
            ]
          },
          "unit": "short"
        },
        "overrides": []
      },
      "gridPos": { "h": 4, "w": 4, "x": 4, "y": 1 },
      "id": 2,
      "options": {
        "colorMode": "value",
        "graphMode": "none",
        "justifyMode": "auto",
        "orientation": "auto",
        "reduceOptions": { "calcs": ["lastNotNull"], "fields": "", "values": false },
        "textMode": "auto"
      },
      "pluginVersion": "10.2.0",
      "targets": [
        {
          "expr": "tavana_adaptive_hpa_min_replicas",
          "legendFormat": "Min",
          "refId": "A"
        }
      ],
      "title": "HPA Min Replicas",
      "type": "stat"
    },
    {
      "datasource": { "type": "prometheus", "uid": "prometheus" },
      "fieldConfig": {
        "defaults": {
          "color": { "mode": "thresholds" },
          "mappings": [],
          "thresholds": {
            "mode": "absolute",
            "steps": [
              { "color": "blue", "value": null }
            ]
          },
          "unit": "short"
        },
        "overrides": []
      },
      "gridPos": { "h": 4, "w": 4, "x": 8, "y": 1 },
      "id": 3,
      "options": {
        "colorMode": "value",
        "graphMode": "none",
        "justifyMode": "auto",
        "orientation": "auto",
        "reduceOptions": { "calcs": ["lastNotNull"], "fields": "", "values": false },
        "textMode": "auto"
      },
      "pluginVersion": "10.2.0",
      "targets": [
        {
          "expr": "tavana_adaptive_hpa_max_replicas",
          "legendFormat": "Max",
          "refId": "A"
        }
      ],
      "title": "HPA Max Replicas",
      "type": "stat"
    },
    {
      "datasource": { "type": "prometheus", "uid": "prometheus" },
      "fieldConfig": {
        "defaults": {
          "color": { "mode": "palette-classic" },
          "mappings": [],
          "thresholds": {
            "mode": "absolute",
            "steps": [
              { "color": "green", "value": null }
            ]
          },
          "unit": "percentunit"
        },
        "overrides": []
      },
      "gridPos": { "h": 4, "w": 4, "x": 12, "y": 1 },
      "id": 4,
      "options": {
        "colorMode": "value",
        "graphMode": "area",
        "justifyMode": "auto",
        "orientation": "auto",
        "reduceOptions": { "calcs": ["lastNotNull"], "fields": "", "values": false },
        "textMode": "auto"
      },
      "pluginVersion": "10.2.0",
      "targets": [
        {
          "expr": "tavana_worker_pool_cpu_utilization",
          "legendFormat": "CPU",
          "refId": "A"
        }
      ],
      "title": "Worker CPU Util",
      "type": "stat"
    },
    {
      "datasource": { "type": "prometheus", "uid": "prometheus" },
      "fieldConfig": {
        "defaults": {
          "color": { "mode": "palette-classic" },
          "mappings": [],
          "thresholds": {
            "mode": "absolute",
            "steps": [
              { "color": "green", "value": null }
            ]
          },
          "unit": "percentunit"
        },
        "overrides": []
      },
      "gridPos": { "h": 4, "w": 4, "x": 16, "y": 1 },
      "id": 5,
      "options": {
        "colorMode": "value",
        "graphMode": "area",
        "justifyMode": "auto",
        "orientation": "auto",
        "reduceOptions": { "calcs": ["lastNotNull"], "fields": "", "values": false },
        "textMode": "auto"
      },
      "pluginVersion": "10.2.0",
      "targets": [
        {
          "expr": "tavana_worker_pool_memory_utilization",
          "legendFormat": "Memory",
          "refId": "A"
        }
      ],
      "title": "Worker Memory Util",
      "type": "stat"
    },
    {
      "datasource": { "type": "prometheus", "uid": "prometheus" },
      "fieldConfig": {
        "defaults": {
          "color": { "mode": "palette-classic" },
          "mappings": [],
          "thresholds": {
            "mode": "absolute",
            "steps": [
              { "color": "green", "value": null }
            ]
          },
          "unit": "short"
        },
        "overrides": []
      },
      "gridPos": { "h": 4, "w": 4, "x": 20, "y": 1 },
      "id": 6,
      "options": {
        "colorMode": "value",
        "graphMode": "none",
        "justifyMode": "auto",
        "orientation": "auto",
        "reduceOptions": { "calcs": ["lastNotNull"], "fields": "", "values": false },
        "textMode": "auto"
      },
      "pluginVersion": "10.2.0",
      "targets": [
        {
          "expr": "tavana_ephemeral_pods_active",
          "legendFormat": "Pods",
          "refId": "A"
        }
      ],
      "title": "Active Ephemeral Pods",
      "type": "stat"
    },
    {
      "gridPos": { "h": 1, "w": 24, "x": 0, "y": 5 },
      "id": 101,
      "title": "Threshold & Scaling Over Time",
      "type": "row"
    },
    {
      "datasource": { "type": "prometheus", "uid": "prometheus" },
      "fieldConfig": {
        "defaults": {
          "color": { "mode": "palette-classic" },
          "custom": {
            "axisCenteredZero": false,
            "axisColorMode": "text",
            "axisLabel": "",
            "axisPlacement": "auto",
            "barAlignment": 0,
            "drawStyle": "line",
            "fillOpacity": 20,
            "gradientMode": "none",
            "hideFrom": { "legend": false, "tooltip": false, "viz": false },
            "lineInterpolation": "smooth",
            "lineWidth": 2,
            "pointSize": 5,
            "scaleDistribution": { "type": "linear" },
            "showPoints": "auto",
            "spanNulls": false,
            "stacking": { "group": "A", "mode": "none" },
            "thresholdsStyle": { "mode": "off" }
          },
          "mappings": [],
          "thresholds": { "mode": "absolute", "steps": [{ "color": "green", "value": null }] },
          "unit": "decmbytes"
        },
        "overrides": []
      },
      "gridPos": { "h": 8, "w": 12, "x": 0, "y": 6 },
      "id": 10,
      "options": {
        "legend": { "calcs": ["lastNotNull", "mean"], "displayMode": "table", "placement": "bottom", "showLegend": true },
        "tooltip": { "mode": "multi", "sort": "none" }
      },
      "targets": [
        {
          "expr": "tavana_adaptive_threshold_mb",
          "legendFormat": "Threshold (MB)",
          "refId": "A"
        }
      ],
      "title": "Adaptive Threshold Over Time",
      "type": "timeseries"
    },
    {
      "datasource": { "type": "prometheus", "uid": "prometheus" },
      "fieldConfig": {
        "defaults": {
          "color": { "mode": "palette-classic" },
          "custom": {
            "axisCenteredZero": false,
            "axisColorMode": "text",
            "axisLabel": "",
            "axisPlacement": "auto",
            "barAlignment": 0,
            "drawStyle": "line",
            "fillOpacity": 20,
            "gradientMode": "none",
            "hideFrom": { "legend": false, "tooltip": false, "viz": false },
            "lineInterpolation": "smooth",
            "lineWidth": 2,
            "pointSize": 5,
            "scaleDistribution": { "type": "linear" },
            "showPoints": "auto",
            "spanNulls": false,
            "stacking": { "group": "A", "mode": "none" },
            "thresholdsStyle": { "mode": "off" }
          },
          "mappings": [],
          "thresholds": { "mode": "absolute", "steps": [{ "color": "green", "value": null }] },
          "unit": "short"
        },
        "overrides": []
      },
      "gridPos": { "h": 8, "w": 12, "x": 12, "y": 6 },
      "id": 11,
      "options": {
        "legend": { "calcs": ["lastNotNull"], "displayMode": "table", "placement": "bottom", "showLegend": true },
        "tooltip": { "mode": "multi", "sort": "none" }
      },
      "targets": [
        {
          "expr": "tavana_adaptive_hpa_min_replicas",
          "legendFormat": "HPA Min",
          "refId": "A"
        },
        {
          "expr": "tavana_adaptive_hpa_max_replicas",
          "legendFormat": "HPA Max",
          "refId": "B"
        },
        {
          "expr": "tavana_worker_replicas{state=\"ready\"}",
          "legendFormat": "Ready Workers",
          "refId": "C"
        }
      ],
      "title": "HPA Scaling Over Time",
      "type": "timeseries"
    },
    {
      "gridPos": { "h": 1, "w": 24, "x": 0, "y": 14 },
      "id": 102,
      "title": "Adjustment Factors",
      "type": "row"
    },
    {
      "datasource": { "type": "prometheus", "uid": "prometheus" },
      "fieldConfig": {
        "defaults": {
          "color": { "mode": "palette-classic" },
          "custom": {
            "axisCenteredZero": false,
            "axisColorMode": "text",
            "axisLabel": "",
            "axisPlacement": "auto",
            "barAlignment": 0,
            "drawStyle": "line",
            "fillOpacity": 10,
            "gradientMode": "none",
            "hideFrom": { "legend": false, "tooltip": false, "viz": false },
            "lineInterpolation": "smooth",
            "lineWidth": 2,
            "pointSize": 5,
            "scaleDistribution": { "type": "linear" },
            "showPoints": "never",
            "spanNulls": false,
            "stacking": { "group": "A", "mode": "none" },
            "thresholdsStyle": { "mode": "off" }
          },
          "mappings": [],
          "thresholds": { "mode": "absolute", "steps": [{ "color": "green", "value": null }] },
          "unit": "short"
        },
        "overrides": []
      },
      "gridPos": { "h": 8, "w": 24, "x": 0, "y": 15 },
      "id": 20,
      "options": {
        "legend": { "calcs": ["lastNotNull"], "displayMode": "table", "placement": "right", "showLegend": true },
        "tooltip": { "mode": "multi", "sort": "none" }
      },
      "targets": [
        {
          "expr": "tavana_adaptive_factor{factor_type=\"time\"}",
          "legendFormat": "Time Factor",
          "refId": "A"
        },
        {
          "expr": "tavana_adaptive_factor{factor_type=\"day\"}",
          "legendFormat": "Day Factor",
          "refId": "B"
        },
        {
          "expr": "tavana_adaptive_factor{factor_type=\"load\"}",
          "legendFormat": "Load Factor",
          "refId": "C"
        },
        {
          "expr": "tavana_adaptive_factor{factor_type=\"event\"}",
          "legendFormat": "Event Factor",
          "refId": "D"
        }
      ],
      "title": "Adaptive Adjustment Factors",
      "type": "timeseries"
    },
    {
      "gridPos": { "h": 1, "w": 24, "x": 0, "y": 23 },
      "id": 103,
      "title": "Query Routing",
      "type": "row"
    },
    {
      "datasource": { "type": "prometheus", "uid": "prometheus" },
      "fieldConfig": {
        "defaults": {
          "color": { "mode": "palette-classic" },
          "mappings": [],
          "thresholds": { "mode": "absolute", "steps": [{ "color": "green", "value": null }] }
        },
        "overrides": []
      },
      "gridPos": { "h": 8, "w": 8, "x": 0, "y": 24 },
      "id": 30,
      "options": {
        "legend": { "displayMode": "table", "placement": "right", "showLegend": true, "values": ["value", "percent"] },
        "pieType": "pie",
        "reduceOptions": { "calcs": ["lastNotNull"], "fields": "", "values": false },
        "tooltip": { "mode": "single", "sort": "none" }
      },
      "targets": [
        {
          "expr": "increase(tavana_queries_routed_total[1h])",
          "legendFormat": "{{target}}",
          "refId": "A"
        }
      ],
      "title": "Query Routing Distribution (1h)",
      "type": "piechart"
    },
    {
      "datasource": { "type": "prometheus", "uid": "prometheus" },
      "fieldConfig": {
        "defaults": {
          "color": { "mode": "palette-classic" },
          "custom": {
            "axisCenteredZero": false,
            "axisColorMode": "text",
            "axisLabel": "",
            "axisPlacement": "auto",
            "barAlignment": 0,
            "drawStyle": "bars",
            "fillOpacity": 80,
            "gradientMode": "none",
            "hideFrom": { "legend": false, "tooltip": false, "viz": false },
            "lineInterpolation": "linear",
            "lineWidth": 1,
            "pointSize": 5,
            "scaleDistribution": { "type": "linear" },
            "showPoints": "never",
            "spanNulls": false,
            "stacking": { "group": "A", "mode": "normal" },
            "thresholdsStyle": { "mode": "off" }
          },
          "mappings": [],
          "thresholds": { "mode": "absolute", "steps": [{ "color": "green", "value": null }] },
          "unit": "short"
        },
        "overrides": []
      },
      "gridPos": { "h": 8, "w": 8, "x": 8, "y": 24 },
      "id": 31,
      "options": {
        "legend": { "calcs": [], "displayMode": "list", "placement": "bottom", "showLegend": true },
        "tooltip": { "mode": "multi", "sort": "none" }
      },
      "targets": [
        {
          "expr": "rate(tavana_queries_routed_total[5m])",
          "legendFormat": "{{target}}",
          "refId": "A"
        }
      ],
      "title": "Query Rate by Target",
      "type": "timeseries"
    },
    {
      "datasource": { "type": "prometheus", "uid": "prometheus" },
      "fieldConfig": {
        "defaults": {
          "color": { "mode": "palette-classic" },
          "custom": {
            "fillOpacity": 80,
            "gradientMode": "none",
            "hideFrom": { "legend": false, "tooltip": false, "viz": false },
            "lineWidth": 1
          },
          "mappings": [],
          "thresholds": { "mode": "absolute", "steps": [{ "color": "green", "value": null }] },
          "unit": "decmbytes"
        },
        "overrides": []
      },
      "gridPos": { "h": 8, "w": 8, "x": 16, "y": 24 },
      "id": 32,
      "options": {
        "bucketOffset": 0,
        "legend": { "calcs": [], "displayMode": "list", "placement": "bottom", "showLegend": true }
      },
      "targets": [
        {
          "expr": "tavana_query_estimated_size_mb_bucket",
          "format": "heatmap",
          "legendFormat": "{{le}}",
          "refId": "A"
        }
      ],
      "title": "Query Size Distribution",
      "type": "histogram"
    },
    {
      "gridPos": { "h": 1, "w": 24, "x": 0, "y": 32 },
      "id": 104,
      "title": "Query Performance",
      "type": "row"
    },
    {
      "datasource": { "type": "prometheus", "uid": "prometheus" },
      "fieldConfig": {
        "defaults": {
          "color": { "mode": "palette-classic" },
          "custom": {
            "axisCenteredZero": false,
            "axisColorMode": "text",
            "axisLabel": "",
            "axisPlacement": "auto",
            "barAlignment": 0,
            "drawStyle": "line",
            "fillOpacity": 10,
            "gradientMode": "none",
            "hideFrom": { "legend": false, "tooltip": false, "viz": false },
            "lineInterpolation": "smooth",
            "lineWidth": 2,
            "pointSize": 5,
            "scaleDistribution": { "type": "linear" },
            "showPoints": "never",
            "spanNulls": false,
            "stacking": { "group": "A", "mode": "none" },
            "thresholdsStyle": { "mode": "off" }
          },
          "mappings": [],
          "thresholds": { "mode": "absolute", "steps": [{ "color": "green", "value": null }] },
          "unit": "s"
        },
        "overrides": []
      },
      "gridPos": { "h": 8, "w": 12, "x": 0, "y": 33 },
      "id": 40,
      "options": {
        "legend": { "calcs": ["mean", "max", "p95"], "displayMode": "table", "placement": "bottom", "showLegend": true },
        "tooltip": { "mode": "multi", "sort": "none" }
      },
      "targets": [
        {
          "expr": "histogram_quantile(0.5, rate(tavana_query_latency_seconds_bucket{status=\"success\"}[5m]))",
          "legendFormat": "P50 - {{route}}",
          "refId": "A"
        },
        {
          "expr": "histogram_quantile(0.95, rate(tavana_query_latency_seconds_bucket{status=\"success\"}[5m]))",
          "legendFormat": "P95 - {{route}}",
          "refId": "B"
        },
        {
          "expr": "histogram_quantile(0.99, rate(tavana_query_latency_seconds_bucket{status=\"success\"}[5m]))",
          "legendFormat": "P99 - {{route}}",
          "refId": "C"
        }
      ],
      "title": "Query Latency by Route",
      "type": "timeseries"
    },
    {
      "datasource": { "type": "prometheus", "uid": "prometheus" },
      "fieldConfig": {
        "defaults": {
          "color": { "mode": "palette-classic" },
          "custom": {
            "axisCenteredZero": false,
            "axisColorMode": "text",
            "axisLabel": "",
            "axisPlacement": "auto",
            "barAlignment": 0,
            "drawStyle": "line",
            "fillOpacity": 10,
            "gradientMode": "none",
            "hideFrom": { "legend": false, "tooltip": false, "viz": false },
            "lineInterpolation": "smooth",
            "lineWidth": 2,
            "pointSize": 5,
            "scaleDistribution": { "type": "linear" },
            "showPoints": "never",
            "spanNulls": false,
            "stacking": { "group": "A", "mode": "none" },
            "thresholdsStyle": { "mode": "off" }
          },
          "mappings": [],
          "thresholds": { "mode": "absolute", "steps": [{ "color": "green", "value": null }] },
          "unit": "short"
        },
        "overrides": []
      },
      "gridPos": { "h": 8, "w": 12, "x": 12, "y": 33 },
      "id": 41,
      "options": {
        "legend": { "calcs": ["sum"], "displayMode": "table", "placement": "bottom", "showLegend": true },
        "tooltip": { "mode": "multi", "sort": "none" }
      },
      "targets": [
        {
          "expr": "rate(tavana_query_throughput_total[5m])",
          "legendFormat": "{{status}}",
          "refId": "A"
        }
      ],
      "title": "Query Throughput by Status",
      "type": "timeseries"
    },
    {
      "gridPos": { "h": 1, "w": 24, "x": 0, "y": 41 },
      "id": 105,
      "title": "Ephemeral Pods",
      "type": "row"
    },
    {
      "datasource": { "type": "prometheus", "uid": "prometheus" },
      "fieldConfig": {
        "defaults": {
          "color": { "mode": "palette-classic" },
          "custom": {
            "axisCenteredZero": false,
            "axisColorMode": "text",
            "axisLabel": "",
            "axisPlacement": "auto",
            "barAlignment": 0,
            "drawStyle": "line",
            "fillOpacity": 20,
            "gradientMode": "none",
            "hideFrom": { "legend": false, "tooltip": false, "viz": false },
            "lineInterpolation": "smooth",
            "lineWidth": 2,
            "pointSize": 5,
            "scaleDistribution": { "type": "linear" },
            "showPoints": "never",
            "spanNulls": false,
            "stacking": { "group": "A", "mode": "none" },
            "thresholdsStyle": { "mode": "off" }
          },
          "mappings": [],
          "thresholds": { "mode": "absolute", "steps": [{ "color": "green", "value": null }] },
          "unit": "s"
        },
        "overrides": []
      },
      "gridPos": { "h": 8, "w": 12, "x": 0, "y": 42 },
      "id": 50,
      "options": {
        "legend": { "calcs": ["mean", "max"], "displayMode": "table", "placement": "bottom", "showLegend": true },
        "tooltip": { "mode": "multi", "sort": "none" }
      },
      "targets": [
        {
          "expr": "histogram_quantile(0.5, rate(tavana_ephemeral_pod_startup_seconds_bucket[5m]))",
          "legendFormat": "P50 Startup",
          "refId": "A"
        },
        {
          "expr": "histogram_quantile(0.95, rate(tavana_ephemeral_pod_startup_seconds_bucket[5m]))",
          "legendFormat": "P95 Startup",
          "refId": "B"
        },
        {
          "expr": "histogram_quantile(0.5, rate(tavana_ephemeral_pod_duration_seconds_bucket[5m]))",
          "legendFormat": "P50 Duration",
          "refId": "C"
        },
        {
          "expr": "histogram_quantile(0.95, rate(tavana_ephemeral_pod_duration_seconds_bucket[5m]))",
          "legendFormat": "P95 Duration",
          "refId": "D"
        }
      ],
      "title": "Ephemeral Pod Timing",
      "type": "timeseries"
    },
    {
      "datasource": { "type": "prometheus", "uid": "prometheus" },
      "fieldConfig": {
        "defaults": {
          "color": { "mode": "palette-classic" },
          "custom": {
            "fillOpacity": 80,
            "gradientMode": "none",
            "hideFrom": { "legend": false, "tooltip": false, "viz": false },
            "lineWidth": 1
          },
          "mappings": [],
          "thresholds": { "mode": "absolute", "steps": [{ "color": "green", "value": null }] },
          "unit": "decmbytes"
        },
        "overrides": []
      },
      "gridPos": { "h": 8, "w": 12, "x": 12, "y": 42 },
      "id": 51,
      "options": {
        "bucketOffset": 0,
        "legend": { "calcs": [], "displayMode": "list", "placement": "bottom", "showLegend": true }
      },
      "targets": [
        {
          "expr": "tavana_ephemeral_pod_memory_mb_bucket",
          "format": "heatmap",
          "legendFormat": "{{le}}",
          "refId": "A"
        }
      ],
      "title": "Ephemeral Pod Memory Distribution",
      "type": "histogram"
    },
    {
      "gridPos": { "h": 1, "w": 24, "x": 0, "y": 50 },
      "id": 106,
      "title": "Estimation Accuracy",
      "type": "row"
    },
    {
      "datasource": { "type": "prometheus", "uid": "prometheus" },
      "fieldConfig": {
        "defaults": {
          "color": { "mode": "palette-classic" },
          "custom": {
            "fillOpacity": 80,
            "gradientMode": "none",
            "hideFrom": { "legend": false, "tooltip": false, "viz": false },
            "lineWidth": 1
          },
          "mappings": [],
          "thresholds": { "mode": "absolute", "steps": [{ "color": "green", "value": null }] },
          "unit": "short"
        },
        "overrides": []
      },
      "gridPos": { "h": 8, "w": 12, "x": 0, "y": 51 },
      "id": 60,
      "options": {
        "bucketOffset": 0,
        "legend": { "calcs": [], "displayMode": "list", "placement": "bottom", "showLegend": true }
      },
      "targets": [
        {
          "expr": "tavana_estimation_accuracy_ratio_bucket",
          "format": "heatmap",
          "legendFormat": "{{le}}",
          "refId": "A"
        }
      ],
      "title": "Estimation Accuracy (Actual/Estimated)",
      "type": "histogram"
    },
    {
      "datasource": { "type": "prometheus", "uid": "prometheus" },
      "fieldConfig": {
        "defaults": {
          "color": { "mode": "palette-classic" },
          "mappings": [],
          "thresholds": { "mode": "absolute", "steps": [{ "color": "green", "value": null }] }
        },
        "overrides": []
      },
      "gridPos": { "h": 8, "w": 12, "x": 12, "y": 51 },
      "id": 61,
      "options": {
        "legend": { "displayMode": "table", "placement": "right", "showLegend": true, "values": ["value", "percent"] },
        "pieType": "pie",
        "reduceOptions": { "calcs": ["lastNotNull"], "fields": "", "values": false },
        "tooltip": { "mode": "single", "sort": "none" }
      },
      "targets": [
        {
          "expr": "sum by (method) (increase(tavana_estimation_method_total[1h]))",
          "legendFormat": "{{method}}",
          "refId": "A"
        }
      ],
      "title": "Estimation Methods Used (1h)",
      "type": "piechart"
    }
  ],
  "refresh": "10s",
  "schemaVersion": 38,
  "style": "dark",
  "tags": ["tavana", "adaptive-scaling", "duckdb"],
  "templating": { "list": [] },
  "time": { "from": "now-1h", "to": "now" },
  "timepicker": {},
  "timezone": "",
  "title": "Tavana Adaptive Scaling",
  "uid": "tavana-adaptive",
  "version": 1,
  "weekStart": ""
}

